samps/__init__.py
samps/asynchronous.py
samps/baudrate.py
samps/common.py
samps/crc.py
samps/errors.py
samps/handlers.py
samps/ports.py
samps/py.typed
samps/tty.py
samps/utilities.py
samps-0.8.0.dist-info/METADATA
samps-0.8.0.dist-info/WHEEL
samps-0.8.0.dist-info/licenses/LICENSE
samps-0.8.0.dist-info/RECORD
