Metadata-Version: 2.4
Name: samps
Version: 0.8.0
Summary: A hypermodern, type-safe, zero-dependency python library for serial port I/O access
Author-email: michealroberts <michael@observerly.com>
License: MIT License
License-File: LICENSE
Keywords: baudrate,io,rs-232,rs-485,serial,tty,uart,usb
Classifier: Development Status :: 4 - Beta
Classifier: Framework :: AsyncIO
Classifier: Intended Audience :: Developers
Classifier: Intended Audience :: System Administrators
Classifier: License :: OSI Approved :: MIT License
Classifier: Operating System :: MacOS :: MacOS X
Classifier: Operating System :: POSIX :: Linux
Classifier: Operating System :: Unix
Classifier: Programming Language :: Python :: 3.10
Classifier: Programming Language :: Python :: 3.11
Classifier: Programming Language :: Python :: 3.12
Classifier: Programming Language :: Python :: 3.13
Classifier: Topic :: Software Development
Classifier: Topic :: Software Development :: Libraries
Classifier: Topic :: Software Development :: Libraries :: Python Modules
Classifier: Topic :: Terminals :: Serial
Classifier: Typing :: Typed
Requires-Python: >=3.10
